odoo/addons/shopinvader_api_payment_provider_sips/README.rst
odoo/addons/shopinvader_api_payment_provider_sips/__init__.py
odoo/addons/shopinvader_api_payment_provider_sips/__manifest__.py
odoo/addons/shopinvader_api_payment_provider_sips/i18n/shopinvader_api_payment_provider_sips.pot
odoo/addons/shopinvader_api_payment_provider_sips/models/__init__.py
odoo/addons/shopinvader_api_payment_provider_sips/models/payment_transaction_sips.py
odoo/addons/shopinvader_api_payment_provider_sips/readme/CONTRIBUTORS.rst
odoo/addons/shopinvader_api_payment_provider_sips/readme/USAGE.rst
odoo/addons/shopinvader_api_payment_provider_sips/routers/__init__.py
odoo/addons/shopinvader_api_payment_provider_sips/routers/payment_sips.py
odoo_addon_shopinvader_api_payment_provider_sips-16.0.1.0.0.8.dist-info/METADATA
odoo_addon_shopinvader_api_payment_provider_sips-16.0.1.0.0.8.dist-info/WHEEL
odoo_addon_shopinvader_api_payment_provider_sips-16.0.1.0.0.8.dist-info/top_level.txt
odoo_addon_shopinvader_api_payment_provider_sips-16.0.1.0.0.8.dist-info/RECORD
